bitsv_data/__init__.py
bitsv_data/blockchain.py
bitsv_data-0.1.1.dist-info/AUTHORS.rst
bitsv_data-0.1.1.dist-info/LICENSE
bitsv_data-0.1.1.dist-info/METADATA
bitsv_data-0.1.1.dist-info/WHEEL
bitsv_data-0.1.1.dist-info/top_level.txt
bitsv_data-0.1.1.dist-info/RECORD
