Metadata-Version: 2.1
Name: bitsv-data
Version: 0.1.1
Summary: Easily store your data on Bitcoin SV
Home-page: https://github.com/joshua-s/bitsv-data
Author: Joshua Smith
Author-email: josh@joshsmith.codes
License: MIT license
Keywords: bitsv_data
Platform: UNKNOWN
Classifier: Development Status :: 2 - Pre-Alpha
Classifier: Intended Audience :: Developers
Classifier: License :: OSI Approved :: MIT License
Classifier: Natural Language :: English
Classifier: Programming Language :: Python :: 3
Classifier: Programming Language :: Python :: 3.5
Classifier: Programming Language :: Python :: 3.6
Classifier: Programming Language :: Python :: 3.7
Requires-Dist: bitsv
